YAPBWD/YAPBWD.py
YAPBWD/__init__.py
YAPBWD-0.0.1.dist-info/LICENSE
YAPBWD-0.0.1.dist-info/METADATA
YAPBWD-0.0.1.dist-info/WHEEL
YAPBWD-0.0.1.dist-info/top_level.txt
YAPBWD-0.0.1.dist-info/RECORD
