Metadata-Version: 2.1
Name: YAPBWD
Version: 0.0.1
Summary: Yet Another Profiler But With Decorators
Home-page: https://github.com/SergSel2006/YAPBWD
Author: Serg_Sel
Author-email: seregasel44@gmail.com
License: UNKNOWN
Project-URL: Bug Tracker, https://github.com/SergSel2006/YAPBWD/issues
Platform: UNKNOWN
Classifier: Programming Language :: Python :: 3
Classifier: License :: OSI Approved :: GNU General Public License v3 or later (GPLv3+)
Classifier: Operating System :: OS Independent
Requires-Python: >=3.6
License-File: LICENSE
